pkg1/__init__.py
pkg1/handler.py
pkg2/__init__.py
pkg2/handler.py
kart_python_pkg-0.1.0.dist-info/METADATA
kart_python_pkg-0.1.0.dist-info/WHEEL
kart_python_pkg-0.1.0.dist-info/top_level.txt
kart_python_pkg-0.1.0.dist-info/RECORD
