Metadata-Version: 2.1
Name: kart-python-pkg
Version: 0.1.0
Summary: Test Python Pkg
Home-page: UNKNOWN
Author: Karthik Venkataraman
Author-email: karthikvenkatraman@gmail.com
License: UNKNOWN
Platform: UNKNOWN
